textcleanser/__init__.py
textcleanser/dialect.py
textcleanser/test.py
textcleanser/textcleanser.py
textcleanser/utils.py
textcleanser-0.0.1.dist-info/DESCRIPTION.rst
textcleanser-0.0.1.dist-info/METADATA
textcleanser-0.0.1.dist-info/RECORD
textcleanser-0.0.1.dist-info/WHEEL
textcleanser-0.0.1.dist-info/metadata.json
textcleanser-0.0.1.dist-info/top_level.txt
textcleanser-0.0.1.dist-info/zip-safe
textprep/__init__.py
textprep/dialect.py
textprep/test.py
textprep/textprep.py
textprep/utils.py
textprep/lexicon/README.txt
textprep/lexicon/corpus.v1.2.tweet
