Metadata-Version: 2.0
Name: textcleanser
Version: 0.0.1
Summary: General preprocessing for text
Home-page: https://github.com/phantomkidding/textcleanser
Author: cchen
Author-email: phantomkidding@gmail.com
License: MIT License
Keywords: text
Platform: any
